{
    "epochs": 2000,
    "batch_size": 4,
    "seq_length": 50,
    "learning_rate": 0.001,
    "vocab_size": 64,
    "embedding_dim": 256,
    "lstm_units": 256,
    "original_model (summary)": {
        "embedding": {
            "type": "Embedding",
            "output_shape": [
                4,
                null,
                256
            ],
            "n_params": 16384
        },
        "lstm": {
            "type": "LSTM",
            "output_shape": [
                4,
                null,
                256
            ],
            "n_params": 525312
        },
        "dense": {
            "type": "Dense",
            "output_shape": [
                4,
                null,
                64
            ],
            "n_params": 16448
        }
    },
    "train categorical cross-entropy loss": 1.402741551399231,
    "train perplexity (2**)": 2.6440355076175543,
    "train perplexity (exp)": 4.066332817077637,
    "test categorical cross-entropy loss": 1.1392511129379272,
    "test perplexity (2**)": 2.2026665550622564,
    "test perplexity (exp)": 3.124427556991577,
    "generative_model (summary)": {
        "embedding_1": {
            "type": "Embedding",
            "output_shape": [
                1,
                null,
                256
            ],
            "n_params": 16384
        },
        "lstm_1": {
            "type": "LSTM",
            "output_shape": [
                1,
                null,
                256
            ],
            "n_params": 525312
        },
        "dense_1": {
            "type": "Dense",
            "output_shape": [
                1,
                null,
                64
            ],
            "n_params": 16448
        }
    },
    "generated_songs_abc": [
        "X:18!B-987]1![_u^nmxoy(<#zn[#\"p8x!V)sK5lut0Kmil<rl9!o-o0-9l#0m=\nKxp!'(XolVrR)xC])9jl/)n[os1lxVl]xL]4!1pnG6RRVK_Mx#o[]9D>)xj<tp6)(_X))C)m]Mmn>uxil#y\"\"z76Mx/p4KGMrum)Mu#lRr#RR<Vz#yjV:jplMz8nLu)p!p]d<|Mx9RX8no6x0Mn)p(Rstp<(xn)iR<)X-u]sixx\"X)([]]X]xMn'x)o-7zzzs)pxn\n_lm'm9u=y\"nsympVsin)oxst,r_4yox4]Kupp>-^uLry]>xz#l[z55!5#nnlLRxnV)<'-sX:>'<94xmlx/rjMVLi4VsV)1mtj[]dcK/<b gcB GF|edB A2:|!\nE|G2B A2G|ARcd 3d|dcB A3|AGE GEE|GEE G3A|BEBG EGED|!\nGAd^c dcdf|edcA G2:|!\nd|cdef fefd|efaf e2fg|eaag egdB|cBAe f2af|ggea bgea|!\nfefe dBAF|EFEF (2FAB c2a|efe (3bagaf fedc|BGAG Adfg|acdB AGEG|B,ED2 c2A2|!\nG2BG ABG2|ded2 Bcd|eaa gef|edc B2A|BGB dBA|GE|!\nGEE BAB|ABd gfe|dBG BEE|!\nEGB ABcd|dcBA A2E|EEE EAe fef|agf fed|ba2 a2|b3 ag|!\ndc dc|d4 d2|AB|c2=f gf2d|eBdB 3de|!\nfdfa fec|d2c ABc|AFA dcAB|Age AAG2GE|E2GF G2:|!",
        "X:68\nM:C\nL:1/8\nK:A Mixolydian\nA|FAA FAdf|eAcA eAAE|eAcA BdBA|eAA2 cdeced|cAFE ED:|D3 GFD2:|!",
        "X:84!nx7xnKllRs0sVy>su(6)LGDtXLx9LL-o8(m)VX8x)[XjKo)V>9##>-<zu>[z#n7Rr06Vxt--1]_o6]zpn,\"pVKopRu\"!XtxjV)X#9LxoxlnpLl#LnpKllrlrrzbVXmx\"_u[[](X6xyysimX7Rl)Xxl]m-8nnnit#)l#Rn)0RxX,xl(XVVMxpln)X)nptKxl]6]\"(X#znrlXjiCVV1[#m])RuK\"xy-#r)LLl\"7Kru>>#<p\n4LxXnx#(L(^u!<L1-)zb\"mmx5o)K\"jLLL8x0<[Lzt]<liVn#sl!)pRp-0-,z]6lo)ujXx)()!(u>K]oM\"xV7p(m!Vxll<MlXrxllxpxRto3ux#mEs3ll)1x)#M##pp(lRC#Vn(]x]ssn'))--V)))b:jKtjxlpn<polo]#\")[jL7jMnss)<6KRtoV)'r[_mM_s1zl#3z]usVnR)>V6np))tM1znV6_,sX'y)m<)lb<9<7_c0u[p)GX9V<9<V7zx_\">-8]Rn5Vmm|ayp]sX(#t/#9))5K!])]p:M)7m9tzVx([M(rxx)0j=b'()](m1]R9^yVyX[Kl-xxAR6[Krzz)trrVus] X#XnoVXuKmLKumix)CXp)C!ls1Mr)rtVplxjzzxD(jnjolxr<j#1)]V[B[#zljpmtV_mmx((XK^-1]K08pm-Ry<jXn[(D>7LxumL/Lnu)z)l<>1[])]y#u>M#MKzl/4uxpio9]l):)-xmXLmu]mF,_X)'n#[1Rp!g7-g^[)<lx]6l]x1M)x-blixK]n7rzX]pjuxynX0Xr:G'5y[]Cj\"Xxp]#xu##jurmX)fjl#5lz)<X-L(!n,nxlll)lKo[R0n6r[lls=/xMn[4M\"]p6mxzn1]6]p]<ynxKx]VV]1Lx<uCLltyVlzVKXGtrXp)!mr[b\",ts_>uc![[,00\"]V2-sxL)x0CR\"nr8:!n8]Rnn[#z!y5#-",
        "X:C5Cl)-z!(\"')s)Kxy<X\n\"#Rs0)t9!Lj#L]1yu/#i]l])-#-9\"#-8xm<ppu9<sny>M\"xp5M)tnLxsrL1BRuxmot86]9n<u9)-upLxR1xs>uMR6)(p\"sypK_9V)l-ty5sRs#X<umXlnbuzup#)Mst-zsz]-p9>9]<RLs#rmlnK5r]<!G]Xnx!]\nM:y8u1oE\"p[pz9x5tlxLn))()Vpjj)jXlt)lxnmo\"pV1V0[pil]><(xzxlntV)My0V\nnA<pKKzt14[MXnMuxz)_M(nR)xXnmpuVXFnt<spXm[Mzlx]ozozuVt/\"pXjrMrMxjtR))5\"to<tVy-0e)mpi5ssnsm!)sl)#(p))R>zX<)_bn'X()RXnprr#a]<1#sRV9f#L!s6LKppXxp)'jpr<LlXyKzXzXLxXLlx-Lxl]yi_XXru)pmRxXrs<0lnn])E! imXl(xoV<-#0pnpl0ry:\"]#)<tx]#nVx<)lR<rt!-)\"o/lxKl)))-o<)LulRKRos-p(DiixxxL)5y)#gp7V#R)>)ut)1V)KLyVb\"VzVKX(u4))mLr]<u#)s'Rm^]X)Rm\nB^s]xt]l])nrKd)x)=uKix)[xxKbl#sslt,XRmi[Xm)o]x5Xo5Kp)mpxnrtsXojK<<!gn]#>^Kol)rj<DVsRVyMyx'RnLuz\"(y)z)xKV\")mXlljxX\"5,l#x]Cx]_<#xLlo>Ls#KXyXLKKMx4nVxlj!rmrVlui<)ux-6\"oxn]#)<9R)^0R]5<lpMVrxKRot]<7ru#lmxjsoy5X=y6u,)[pRRo4<y3'-4ol)uKo>Mmpz9<9ex<#)s4yx5pX7))zVlx>#X#6ltoRu=xXnj(\"bm-)oRLm4m!on-! Rz>ef/d/e/|fdcA BAF|E3 AFG|dAF GFA|!\ncee ecA|dcd edc|dAB c2d|AF DFA|dfe dBG|cAF GEE|!\ndcd ABc|d3 eAc|AGE E2:|!",
        "X:1<8KMso4[L)l)Alyl(7XsnL]5<RR0X)<y]'u)4lpuVx0r#VX)z7#Lnx\"[]<p)oM\"xp5xl)ss)x]XVm6xnpzXujp#txpRx\"()XV)^s<#'x-lV)VV(#[[]Voyx-yx0z-lx/rnx<<uy]y#pR)]'85rrzpnlRLxp)])moLVRms)y#9Kx(gV,x<)]po)u>)MKlVp)L#\"LjXXoL8y0l9mrp)#!)x]8xnslyl=]r']xKXtxz(s),r]r<K!ypr-Xs-rnCob]VjL[j>KC<ELxXpu#)Rll)\"z]>Vu]5VjsuR3]L-^0u06])r,))jj4]R[RX9])]Vm[y-7]jlp)\"rtzVi<)Vob<(l)uuR<p)m<<'R))es-KFo4F]> 0jl)VXRKx\"X(r:o4xp]L5o\")yRuX]nx(n5]u-z9][jXLVy2LlzKV_y(en-ai-xo#nznrrm)-4#pz9<-RR><RR_9#e7M\"m0[]g#]^68-)t))<muV>9M_[ys]lX4x0zr7uxx\"K5!u-oplxR(p#)6)z99-y-j<( !]]1y17olil]xx3jtnm](5u][]n#m]K(#'V'x))L]L]17!<)_1l'n\"p]-9]dVLLszlXpsoVj)Voy4MuLxpXr<xxRt/ilp=RjjXXRVxzM8sz8b]xn#uz<#Li>y8<))xtzy<<#tps>smt#]r->p(jBMtVxoVns)RRnx\"iM#>uozu)#)\nuX19L7-<]R9[(sn)R#u]i0(VxLx5<mmm<#pljou[\"0<\"5ppuxz<Vs\"u9^jRoRr5z]lmuts#X)xjmprsV)XlR#RX\"pLXu]X4],!!y]l>z16]-nnr",
        "X:18LXMX)s1))K#mf))lxl)yerl\"Xnyuz)#tR)#'L#lX#uC]j:<m\"#-Vson<]6V#>),z8Llr)l8p<R1#-3j)<XMnR(z-ooVLp]ons)0l)y5zll<(#<0)_\"#zr]l##M(l)m)\"7pC]Xxxtx)xxL]puxK<xL7]l]s)xn x:L8u'rls>4]#u]]--B>A/F/D/|!\nAdcA de^c d2A|GEE EEE|F2E|D2D AFD|DFG dcB|c2B cBAF FGEF GEE:|!\n[|\nX:31 a3 df|eg f2 d>e|fd g2 f2|!\nD2B2 eef gab|afg dfe|fdA AFD|!\nB3 gB|AgBc dBAG|FADF D2:|!\nd|d^cde fde2|f3b an\n(3ec|dcA AGE|F2E FGE|DB,\nM:C\nL:1/8\nK:D Major\nD2FA dcAF|E2EF F2DF|DFAF B2AB|AGAA BcAG|!\nB3d eaa|bga ged|cAA cAA|FAB c2A|d2d dcG|F2D D2:|!\n|EBA ABd|Ade fdd|cAG FED:|!",
        "X:21\nM:6/8\nL:1/8\nK:A Dorian\nD|E2E G2B|A3 A2:|!",
        "X:21\nM:6/8\nL:1/8\nK:D Major\nD|E2GB cABc|AcBc ADEG|Aded cAGA|BdBA BGBA BGE|]!\nK:A D2F D2F|DEE E2D|CA, EEA|gfe d2e|fgf d2:|!\naa gf|af|g3 fe|fdd ecA|fef f2f|edB A2|!\ngdB B2d|AF F2F|!\nCFC EEF|EcD GFd|AGF E2:|!",
        "X:374\nM:C\nL:1/8\nK:D Major\nDE|EFAF FEFA|B2A2 F2DF|DAB AAc|B2]!",
        "X:984(bf>n]3n\n-L)smuXgVL]g\n:1]5#nx)jLxLVjxlLl))\"X7llp)i# lKlrr)jRt>-]6pKRGF-!m1A/1pR)!"
    ],
    "original_model": "{\"class_name\": \"Sequential\", \"config\": {\"name\": \"sequential\", \"layers\": [{\"class_name\": \"InputLayer\", \"config\": {\"batch_input_shape\": [4, null], \"dtype\": \"float32\", \"sparse\": false, \"ragged\": false, \"name\": \"embedding_input\"}}, {\"class_name\": \"Embedding\", \"config\": {\"name\": \"embedding\", \"trainable\": true, \"batch_input_shape\": [4, null], \"dtype\": \"float32\", \"input_dim\": 64, \"output_dim\": 256, \"embeddings_initializer\": {\"class_name\": \"RandomUniform\", \"config\": {\"minval\": -0.05, \"maxval\": 0.05, \"seed\": null}}, \"embeddings_regularizer\": null, \"activity_regularizer\": null, \"embeddings_constraint\": null, \"mask_zero\": false, \"input_length\": null}}, {\"class_name\": \"LSTM\", \"config\": {\"name\": \"lstm\", \"trainable\": true, \"dtype\": \"float32\", \"return_sequences\": true, \"return_state\": false, \"go_backwards\": false, \"stateful\": true, \"unroll\": false, \"time_major\": false, \"units\": 256, \"activation\": \"tanh\", \"recurrent_activation\": \"sigmoid\", \"use_bias\": true, \"kernel_initializer\": {\"class_name\": \"GlorotUniform\", \"config\": {\"seed\": null}}, \"recurrent_initializer\": {\"class_name\": \"GlorotUniform\", \"config\": {\"seed\": null}}, \"bias_initializer\": {\"class_name\": \"Zeros\", \"config\": {}}, \"unit_forget_bias\": true, \"kernel_regularizer\": null, \"recurrent_regularizer\": null, \"bias_regularizer\": null, \"activity_regularizer\": null, \"kernel_constraint\": null, \"recurrent_constraint\": null, \"bias_constraint\": null, \"dropout\": 0.0, \"recurrent_dropout\": 0.0, \"implementation\": 2}}, {\"class_name\": \"Dense\", \"config\": {\"name\": \"dense\", \"trainable\": true, \"dtype\": \"float32\", \"units\": 64, \"activation\": \"linear\", \"use_bias\": true, \"kernel_initializer\": {\"class_name\": \"GlorotUniform\", \"config\": {\"seed\": null}}, \"bias_initializer\": {\"class_name\": \"Zeros\", \"config\": {}}, \"kernel_regularizer\": null, \"bias_regularizer\": null, \"activity_regularizer\": null, \"kernel_constraint\": null, \"bias_constraint\": null}}]}, \"keras_version\": \"2.9.0\", \"backend\": \"tensorflow\"}",
    "train loss history (from plot)": [
        4.155564785003662,
        4.1457085609436035,
        4.123117446899414,
        4.085318088531494,
        4.0579047203063965,
        3.7790539264678955,
        3.7477893829345703,
        3.265775680541992,
        3.2959892749786377,
        3.646486282348633,
        3.1917614936828613,
        3.497807264328003,
        3.429251194000244,
        2.976975917816162,
        3.313908100128174,
        3.2590482234954834,
        2.9868133068084717,
        3.1414849758148193,
        3.1251862049102783,
        3.18428111076355,
        3.5726122856140137,
        3.282418727874756,
        3.138981342315674,
        3.1056084632873535,
        3.5832695960998535,
        3.153071641921997,
        3.0993051528930664,
        3.282759428024292,
        3.410646438598633,
        3.0032694339752197,
        3.2449402809143066,
        3.0371782779693604,
        3.0981359481811523,
        3.1121246814727783,
        3.0067009925842285,
        3.1584994792938232,
        3.1562726497650146,
        3.2967987060546875,
        3.4051826000213623,
        3.255061626434326,
        2.9847846031188965,
        3.012761116027832,
        3.1265833377838135,
        3.158864736557007,
        3.0644664764404297,
        3.4673705101013184,
        3.0989880561828613,
        3.1767470836639404,
        2.982179641723633,
        2.8234434127807617,
        3.277350425720215,
        3.258946418762207,
        3.1514856815338135,
        2.867905378341675,
        3.324106216430664,
        3.1506056785583496,
        2.962459087371826,
        3.131929397583008,
        3.0935122966766357,
        3.105802536010742,
        3.152242422103882,
        3.0728588104248047,
        3.041973829269409,
        2.9452097415924072,
        2.934211492538452,
        2.9102020263671875,
        3.0847156047821045,
        2.8252880573272705,
        2.864068031311035,
        2.8930578231811523,
        2.701145887374878,
        2.6572186946868896,
        2.860854387283325,
        2.7351605892181396,
        2.7534401416778564,
        2.7541933059692383,
        2.9033501148223877,
        2.812446355819702,
        2.768558979034424,
        2.72080135345459,
        2.6160264015197754,
        2.552680730819702,
        2.665273427963257,
        2.6935014724731445,
        2.7605035305023193,
        2.6865074634552,
        2.677560329437256,
        2.5258235931396484,
        2.8834784030914307,
        2.530546188354492,
        2.5367043018341064,
        2.612910747528076,
        2.7353622913360596,
        2.428218364715576,
        2.655721426010132,
        2.3687894344329834,
        2.351794958114624,
        2.49601674079895,
        2.2736856937408447,
        2.5174081325531006,
        2.423689365386963,
        2.6421592235565186,
        2.4893457889556885,
        2.3252298831939697,
        2.5425848960876465,
        2.3245317935943604,
        2.3832955360412598,
        2.4572837352752686,
        2.3857250213623047,
        2.3873791694641113,
        2.3599436283111572,
        2.3959898948669434,
        2.3309333324432373,
        2.3801681995391846,
        2.3446943759918213,
        2.3122055530548096,
        2.4651434421539307,
        2.2803118228912354,
        2.178666830062866,
        2.2646045684814453,
        2.199861526489258,
        2.183387041091919,
        2.3432788848876953,
        2.3803794384002686,
        2.252439260482788,
        2.4066059589385986,
        2.1880033016204834,
        2.3271307945251465,
        2.10176157951355,
        2.0786423683166504,
        2.1056549549102783,
        2.1754403114318848,
        2.2694458961486816,
        2.2109549045562744,
        2.106485366821289,
        2.1383042335510254,
        2.1410229206085205,
        2.085228443145752,
        2.130892753601074,
        2.0726447105407715,
        2.165435552597046,
        2.1602280139923096,
        2.1973297595977783,
        1.9444546699523926,
        2.6348040103912354,
        1.979040265083313,
        2.2463178634643555,
        2.2111635208129883,
        2.170062780380249,
        2.266345739364624,
        2.219024896621704,
        2.054095506668091,
        2.0747156143188477,
        2.107952833175659,
        2.248347520828247,
        2.2029714584350586,
        2.057887315750122,
        2.157651424407959,
        2.0415494441986084,
        2.068122625350952,
        2.1278023719787598,
        2.5030629634857178,
        2.1241061687469482,
        2.0703012943267822,
        2.0358808040618896,
        2.084782600402832,
        2.1171207427978516,
        2.201658248901367,
        1.9169954061508179,
        2.3627240657806396,
        2.165954828262329,
        1.9113885164260864,
        1.786588191986084,
        2.304487943649292,
        2.3219339847564697,
        2.1187632083892822,
        2.046680212020874,
        1.9921536445617676,
        1.9087741374969482,
        2.0550947189331055,
        1.9002904891967773,
        1.9221986532211304,
        1.9765896797180176,
        1.9301425218582153,
        1.8933802843093872,
        1.9785561561584473,
        1.951548457145691,
        1.9896236658096313,
        1.9284988641738892,
        2.0417661666870117,
        1.9181534051895142,
        1.7907476425170898,
        1.998042345046997,
        1.7964645624160767,
        1.7646678686141968,
        1.8779264688491821,
        1.818434715270996,
        1.7887508869171143,
        2.4097342491149902,
        1.8169429302215576,
        1.8870327472686768,
        1.8404582738876343,
        2.116363763809204,
        2.104768753051758,
        2.235811471939087,
        2.199028968811035,
        2.166050672531128,
        1.8552584648132324,
        1.8680388927459717,
        1.9849697351455688,
        2.125166893005371,
        1.607129693031311,
        2.0384113788604736,
        1.7375149726867676,
        1.8922022581100464,
        1.943088412284851,
        1.7468805313110352,
        1.8187412023544312,
        2.0893940925598145,
        1.9336671829223633,
        1.7577810287475586,
        1.9205917119979858,
        1.6999115943908691,
        1.664839744567871,
        2.052515983581543,
        1.6886361837387085,
        1.8718938827514648,
        1.9849345684051514,
        1.9035125970840454,
        1.848692774772644,
        1.8691848516464233,
        1.8522802591323853,
        1.9644802808761597,
        1.8257681131362915,
        1.8158519268035889,
        1.8081682920455933,
        1.6719378232955933,
        1.4989547729492188,
        1.6642792224884033,
        1.734389305114746,
        1.6455212831497192,
        1.8458682298660278,
        1.9618359804153442,
        1.950533151626587,
        1.4209970235824585,
        1.7570611238479614,
        1.9497954845428467,
        1.8159880638122559,
        1.9560259580612183,
        1.7361807823181152,
        1.6504795551300049,
        1.6235132217407227,
        1.7840945720672607,
        2.0098354816436768,
        1.9688611030578613,
        1.9850738048553467,
        1.8259832859039307,
        2.0404767990112305,
        2.0074002742767334,
        1.827272891998291,
        1.3988995552062988,
        1.8755759000778198,
        1.787532091140747,
        1.6401550769805908,
        1.7215945720672607,
        1.6148873567581177,
        1.6668899059295654,
        1.6852933168411255,
        1.4975180625915527,
        1.6682336330413818,
        2.0270402431488037,
        1.787510633468628,
        1.9184744358062744,
        1.543015718460083,
        1.5631083250045776,
        1.6942095756530762,
        1.9022221565246582,
        2.1329638957977295,
        1.9303641319274902,
        1.9892518520355225,
        1.6570245027542114,
        1.7947124242782593,
        1.680567979812622,
        1.5106090307235718,
        1.8406785726547241,
        1.7332714796066284,
        1.8049768209457397,
        1.8322025537490845,
        1.8909133672714233,
        2.107199192047119,
        1.4904239177703857,
        2.023435354232788,
        1.9915052652359009,
        1.9168953895568848,
        1.588791847229004,
        1.7251837253570557,
        1.797094464302063,
        1.803362250328064,
        1.5162756443023682,
        1.833211064338684,
        1.5597119331359863,
        2.1114590167999268,
        1.6653845310211182,
        1.7060283422470093,
        1.6705081462860107,
        2.0080819129943848,
        1.7688010931015015,
        1.642716646194458,
        1.7461334466934204,
        1.736189603805542,
        1.6441270112991333,
        1.6547125577926636,
        2.0360169410705566,
        1.7508538961410522,
        1.423189640045166,
        1.6273857355117798,
        1.7203423976898193,
        1.7452763319015503,
        1.6857409477233887,
        1.8438711166381836,
        1.344321846961975,
        1.8551931381225586,
        1.5689998865127563,
        1.7033357620239258,
        1.5288522243499756,
        1.6990017890930176,
        1.6239105463027954,
        1.7622641324996948,
        1.7420907020568848,
        1.540440320968628,
        1.8977187871932983,
        1.8797885179519653,
        1.737906813621521,
        1.7607147693634033,
        1.5337201356887817,
        1.697240948677063,
        1.5784133672714233,
        1.9950153827667236,
        1.4774932861328125,
        1.8311445713043213,
        1.6710922718048096,
        1.6041241884231567,
        1.7100660800933838,
        1.7310293912887573,
        1.3999754190444946,
        1.6373974084854126,
        1.8080763816833496,
        1.6522119045257568,
        1.6781096458435059,
        1.6016262769699097,
        1.925243854522705,
        1.5232065916061401,
        1.9756757020950317,
        1.8057208061218262,
        1.8080209493637085,
        1.6899371147155762,
        2.094357967376709,
        1.5628443956375122,
        1.7390092611312866,
        1.8664462566375732,
        1.5094715356826782,
        1.6201844215393066,
        1.5246458053588867,
        1.4522879123687744,
        1.7186203002929688,
        1.8448928594589233,
        1.7116883993148804,
        1.7738409042358398,
        1.7138235569000244,
        1.4715564250946045,
        1.3831908702850342,
        1.786464810371399,
        1.5374464988708496,
        1.3185592889785767,
        1.5955681800842285,
        1.6609845161437988,
        1.5221893787384033,
        1.6736786365509033,
        1.6406725645065308,
        1.6834378242492676,
        1.4859765768051147,
        1.6149210929870605,
        1.7614874839782715,
        1.323583722114563,
        1.6303982734680176,
        1.551970362663269,
        1.420233130455017,
        1.7378289699554443,
        1.7738827466964722,
        1.3903014659881592,
        1.7242199182510376,
        1.6897599697113037,
        1.5379024744033813,
        1.6111586093902588,
        1.3931790590286255,
        1.6540607213974,
        1.6961201429367065,
        1.6379836797714233,
        1.685644507408142,
        1.7846163511276245,
        1.656972050666809,
        1.564710259437561,
        1.597214937210083,
        1.9002493619918823,
        1.9079771041870117,
        1.767799735069275,
        1.5609017610549927,
        1.4072527885437012,
        1.7268463373184204,
        1.5980465412139893,
        1.7514541149139404,
        1.6267504692077637,
        1.831241488456726,
        1.7213863134384155,
        1.3993245363235474,
        1.672227144241333,
        1.4158902168273926,
        1.8283735513687134,
        1.7395199537277222,
        1.8331973552703857,
        1.8009778261184692,
        1.5125330686569214,
        1.808432936668396,
        1.5229458808898926,
        1.4732155799865723,
        1.5943013429641724,
        1.5502407550811768,
        1.4640780687332153,
        1.331081509590149,
        1.5378543138504028,
        1.724156141281128,
        1.89863920211792,
        1.930232286453247,
        1.7311606407165527,
        1.6415085792541504,
        1.4052345752716064,
        1.4373959302902222,
        1.8215317726135254,
        1.8923715353012085,
        1.6804181337356567,
        1.2851300239562988,
        1.8398476839065552,
        1.6644476652145386,
        1.7795559167861938,
        1.6074364185333252,
        1.6726434230804443,
        1.8705358505249023,
        1.7148127555847168,
        1.7426893711090088,
        1.3766677379608154,
        1.7578246593475342,
        1.6796313524246216,
        1.4588960409164429,
        1.5752185583114624,
        1.7158242464065552,
        1.5409854650497437,
        1.7283389568328857,
        1.6313518285751343,
        1.5609921216964722,
        1.3254138231277466,
        1.769463062286377,
        1.6869889497756958,
        1.5923309326171875,
        1.7101632356643677,
        1.6121395826339722,
        1.3929495811462402,
        1.4339118003845215,
        1.759202480316162,
        1.776273250579834,
        1.6175504922866821,
        1.5857189893722534,
        1.5277795791625977,
        2.0891671180725098,
        1.7132213115692139,
        1.4274506568908691,
        1.690346121788025,
        1.7949544191360474,
        1.5396112203598022,
        1.6859846115112305,
        1.62813138961792,
        1.5189472436904907,
        1.4671108722686768,
        1.372542381286621,
        1.7868218421936035,
        1.3083857297897339,
        1.5407437086105347,
        1.5937552452087402,
        1.607102632522583,
        1.8756577968597412,
        1.2863391637802124,
        1.4136477708816528,
        1.8445611000061035,
        1.6260802745819092,
        1.940151333808899,
        1.7439985275268555,
        1.2321990728378296,
        1.6277564764022827,
        1.959330439567566,
        1.5626565217971802,
        1.7277640104293823,
        1.7365225553512573,
        1.657386064529419,
        1.3763680458068848,
        1.6651016473770142,
        1.8916747570037842,
        1.7423855066299438,
        1.5799460411071777,
        1.5097085237503052,
        1.9467178583145142,
        1.6005784273147583,
        1.601373553276062,
        1.6662408113479614,
        1.8425261974334717,
        1.4772250652313232,
        1.5232734680175781,
        1.768735408782959,
        1.656835675239563,
        1.479455590248108,
        1.5865510702133179,
        1.7222795486450195,
        1.572096824645996,
        1.6912274360656738,
        1.5070114135742188,
        1.6560249328613281,
        1.4761013984680176,
        1.49114191532135,
        1.4340109825134277,
        1.4140225648880005,
        1.577750563621521,
        1.7238473892211914,
        1.5036804676055908,
        1.4611847400665283,
        1.3473942279815674,
        1.7066105604171753,
        1.054090976715088,
        1.3433754444122314,
        1.964118242263794,
        1.4340026378631592,
        1.2081083059310913,
        1.3996100425720215,
        1.794488787651062,
        1.2240127325057983,
        1.6519180536270142,
        1.6568832397460938,
        1.5361073017120361,
        1.6500619649887085,
        1.899131417274475,
        1.6337777376174927,
        1.4858899116516113,
        1.6183685064315796,
        1.643113374710083,
        1.5787250995635986,
        1.3154635429382324,
        1.5295361280441284,
        1.9176504611968994,
        1.7292715311050415,
        1.8248062133789062,
        1.7378230094909668,
        1.4284124374389648,
        1.5428234338760376,
        1.709081768989563,
        1.7664425373077393,
        1.6145111322402954,
        1.6728830337524414,
        1.5613921880722046,
        1.6210463047027588,
        1.4176414012908936,
        1.5568088293075562,
        1.6077682971954346,
        1.488828420639038,
        1.3340630531311035,
        1.3606420755386353,
        1.3806337118148804,
        1.545595645904541,
        1.5455560684204102,
        1.5025274753570557,
        1.5448694229125977,
        1.7202239036560059,
        1.7124395370483398,
        2.249498128890991,
        1.4466906785964966,
        1.6329551935195923,
        1.6313821077346802,
        1.6412320137023926,
        1.6861082315444946,
        1.6142421960830688,
        1.3735580444335938,
        1.4442837238311768,
        1.5278120040893555,
        1.2458041906356812,
        1.576743483543396,
        1.7342169284820557,
        1.2975424528121948,
        1.6587988138198853,
        1.6889865398406982,
        1.6467760801315308,
        1.7162022590637207,
        1.7254917621612549,
        1.9532601833343506,
        1.8011517524719238,
        1.3691277503967285,
        1.2782633304595947,
        1.5313032865524292,
        1.7221636772155762,
        1.4476488828659058,
        1.7103604078292847,
        1.6883327960968018,
        1.5009582042694092,
        1.4757790565490723,
        1.6252212524414062,
        1.1814268827438354,
        1.750575304031372,
        1.4302830696105957,
        1.5092445611953735,
        1.4603850841522217,
        1.2672958374023438,
        1.4337185621261597,
        1.2756270170211792,
        1.3963079452514648,
        1.5657751560211182,
        1.33440363407135,
        1.7552036046981812,
        1.906251072883606,
        1.3756768703460693,
        1.9676209688186646,
        1.4546366930007935,
        1.7189102172851562,
        1.683895468711853,
        1.5776292085647583,
        1.843544363975525,
        1.4788391590118408,
        1.3225111961364746,
        1.5480892658233643,
        1.7121834754943848,
        1.3896093368530273,
        1.7716162204742432,
        1.4082797765731812,
        1.5744343996047974,
        1.3092113733291626,
        1.715455174446106,
        1.5475424528121948,
        1.6116948127746582,
        1.6107372045516968,
        1.4370208978652954,
        1.248363971710205,
        1.7159098386764526,
        1.8676178455352783,
        1.6840399503707886,
        1.6191895008087158,
        1.4536328315734863,
        1.778520941734314,
        1.8295927047729492,
        1.735996961593628,
        1.2228683233261108,
        1.5845482349395752,
        1.5214825868606567,
        1.4675123691558838,
        1.490850806236267,
        1.7856117486953735,
        1.3771508932113647,
        1.7726305723190308,
        1.5275993347167969,
        1.3800408840179443,
        1.7486599683761597,
        1.9013055562973022,
        1.3847390413284302,
        1.4065957069396973,
        1.622125506401062,
        1.4878230094909668,
        1.5525293350219727,
        1.6165753602981567,
        1.6855860948562622,
        1.2469191551208496,
        1.2963894605636597,
        1.5584036111831665,
        1.2044720649719238,
        1.6919031143188477,
        1.336794376373291,
        1.6651028394699097,
        1.6504918336868286,
        1.7768378257751465,
        1.5054106712341309,
        1.432296872138977,
        1.6131906509399414,
        1.7531726360321045,
        1.711614966392517,
        1.5232821702957153,
        1.3980157375335693,
        1.4510095119476318,
        1.6044301986694336,
        1.5956262350082397,
        1.7004605531692505,
        1.3678473234176636,
        1.5057162046432495,
        1.4456849098205566,
        1.8315435647964478,
        1.4445905685424805,
        1.2999053001403809,
        1.6090811491012573,
        1.5044379234313965,
        1.6542329788208008,
        1.602175235748291,
        1.7013778686523438,
        1.4640086889266968,
        1.5342812538146973,
        1.456529974937439,
        1.6830302476882935,
        1.5765771865844727,
        1.617648720741272,
        1.6026368141174316,
        1.3695873022079468,
        1.2900702953338623,
        1.4453625679016113,
        1.6233258247375488,
        1.5571818351745605,
        1.3046841621398926,
        1.4904698133468628,
        1.3562884330749512,
        1.445878505706787,
        1.5028138160705566,
        1.3895635604858398,
        1.568717360496521,
        1.4875454902648926,
        1.5286864042282104,
        1.4590835571289062,
        1.5933563709259033,
        1.811205267906189,
        1.4400771856307983,
        1.4274035692214966,
        1.3412305116653442,
        1.4127429723739624,
        1.6370271444320679,
        1.6204290390014648,
        1.7011855840682983,
        1.5009818077087402,
        1.7775992155075073,
        1.4347723722457886,
        1.2524659633636475,
        1.5762437582015991,
        1.5922726392745972,
        1.4958935976028442,
        1.4489370584487915,
        1.5957849025726318,
        1.2046446800231934,
        1.398768663406372,
        1.444879412651062,
        1.5079883337020874,
        1.8344577550888062,
        1.4898587465286255,
        1.6322391033172607,
        1.1448626518249512,
        1.2477413415908813,
        1.684049129486084,
        1.474647879600525,
        1.8580169677734375,
        1.541250467300415,
        1.4189432859420776,
        1.3621773719787598,
        1.3668670654296875,
        1.6231484413146973,
        1.603732705116272,
        1.5735293626785278,
        1.1899898052215576,
        1.341971755027771,
        1.2812689542770386,
        1.513124942779541,
        1.3471592664718628,
        1.4565025568008423,
        1.4665814638137817,
        1.4716928005218506,
        1.257117509841919,
        1.4588165283203125,
        1.22471284866333,
        1.7693476676940918,
        2.0066583156585693,
        1.3327903747558594,
        1.6301366090774536,
        1.5192697048187256,
        1.5251115560531616,
        1.4866225719451904,
        1.704587697982788,
        1.208204984664917,
        1.2713698148727417,
        1.4566885232925415,
        1.5313351154327393,
        1.5247913599014282,
        1.6942576169967651,
        1.4811489582061768,
        1.3913300037384033,
        1.489314317703247,
        1.198594331741333,
        1.5476776361465454,
        1.765213966369629,
        1.5235329866409302,
        1.6544097661972046,
        1.2695832252502441,
        1.6703158617019653,
        1.4677231311798096,
        1.3086318969726562,
        1.8190542459487915,
        1.4946670532226562,
        1.573422908782959,
        1.438478946685791,
        1.5064146518707275,
        1.6639474630355835,
        1.6062277555465698,
        1.6217998266220093,
        1.5097407102584839,
        1.4830316305160522,
        1.7032349109649658,
        1.6458483934402466,
        1.2597280740737915,
        1.3883330821990967,
        1.7540500164031982,
        1.262961983680725,
        1.4126548767089844,
        1.125523567199707,
        1.3355660438537598,
        1.5396332740783691,
        1.5173401832580566,
        1.1596691608428955,
        1.3503211736679077,
        1.5390774011611938,
        1.6001782417297363,
        1.6770135164260864,
        1.4810998439788818,
        1.4988120794296265,
        1.5883140563964844,
        1.5076119899749756,
        1.6557247638702393,
        1.4619919061660767,
        1.4495608806610107,
        1.4953694343566895,
        1.483139991760254,
        1.567499041557312,
        1.7018213272094727,
        1.5342997312545776,
        1.5596386194229126,
        1.2783007621765137,
        1.574804425239563,
        1.3793927431106567,
        1.4218358993530273,
        1.6341681480407715,
        1.5510499477386475,
        1.1262255907058716,
        1.4814397096633911,
        1.4262118339538574,
        1.2866450548171997,
        1.6021826267242432,
        1.399937629699707,
        1.8573898077011108,
        1.3357816934585571,
        1.686680555343628,
        1.4236924648284912,
        1.4498660564422607,
        1.9772714376449585,
        1.4261229038238525,
        1.648769736289978,
        1.482699990272522,
        1.335982322692871,
        1.3866976499557495,
        1.4134604930877686,
        1.5440107583999634,
        1.4177976846694946,
        1.814405918121338,
        1.7584964036941528,
        1.3959600925445557,
        1.589362382888794,
        1.6130166053771973,
        1.8431499004364014,
        1.4074385166168213,
        1.5765411853790283,
        1.5596129894256592,
        1.377946138381958,
        1.245008111000061,
        1.8403685092926025,
        1.6840194463729858,
        1.2144170999526978,
        1.4207490682601929,
        2.0183050632476807,
        1.591536283493042,
        1.4461429119110107,
        1.4600797891616821,
        1.6665459871292114,
        1.5185058116912842,
        1.4455702304840088,
        1.5460505485534668,
        1.3531798124313354,
        1.4863873720169067,
        1.226241946220398,
        1.274242877960205,
        1.4632266759872437,
        1.480615258216858,
        1.2477343082427979,
        1.4015823602676392,
        1.737904667854309,
        1.5297415256500244,
        1.4029687643051147,
        1.4092060327529907,
        1.4171661138534546,
        1.6092807054519653,
        1.39568293094635,
        1.4889696836471558,
        1.3417898416519165,
        1.6053386926651,
        1.5950123071670532,
        1.3960903882980347,
        1.2887402772903442,
        1.4152395725250244,
        1.784041166305542,
        1.1784554719924927,
        1.4065709114074707,
        1.290578007698059,
        1.3595541715621948,
        1.4214882850646973,
        1.8428715467453003,
        1.4445481300354004,
        1.5535554885864258,
        1.4351823329925537,
        1.5516010522842407,
        1.7570306062698364,
        1.8302340507507324,
        1.3831031322479248,
        1.3263654708862305,
        1.766273856163025,
        1.453059196472168,
        1.5486091375350952,
        1.4451137781143188,
        1.5441503524780273,
        1.5279382467269897,
        1.592698335647583,
        1.6204932928085327,
        1.4645313024520874,
        1.6317253112792969,
        1.7396247386932373,
        1.3341553211212158,
        1.2624915838241577,
        1.6214032173156738,
        1.4767181873321533,
        1.4190081357955933,
        1.3582959175109863,
        1.5382027626037598,
        1.379155158996582,
        1.7874243259429932,
        1.364752173423767,
        1.467934012413025,
        1.1691069602966309,
        1.4315812587738037,
        1.480434536933899,
        1.4546027183532715,
        1.2673970460891724,
        1.3388333320617676,
        1.3167797327041626,
        1.3746660947799683,
        1.584708571434021,
        1.9241917133331299,
        1.3028640747070312,
        1.2679513692855835,
        1.4909826517105103,
        1.5591988563537598,
        1.4149585962295532,
        1.528996229171753,
        1.247999668121338,
        1.4990246295928955,
        1.4781463146209717,
        1.5150829553604126,
        1.7942630052566528,
        1.761776089668274,
        1.6143543720245361,
        1.5508172512054443,
        1.686720609664917,
        1.6236745119094849,
        1.3592277765274048,
        1.635698676109314,
        1.7201910018920898,
        1.3800311088562012,
        1.5407235622406006,
        1.669132947921753,
        1.4417948722839355,
        1.2394027709960938,
        1.5820481777191162,
        1.2858995199203491,
        1.5098870992660522,
        1.3604018688201904,
        1.3503707647323608,
        1.3260869979858398,
        1.4343655109405518,
        1.6738842725753784,
        1.574944257736206,
        1.3926283121109009,
        1.2198717594146729,
        1.433925747871399,
        1.3743069171905518,
        1.533951759338379,
        1.7000008821487427,
        1.4598318338394165,
        1.2551429271697998,
        1.3059897422790527,
        1.6450586318969727,
        1.4357850551605225,
        1.486596703529358,
        1.200942873954773,
        1.2483769655227661,
        1.2982916831970215,
        1.4294514656066895,
        1.7003376483917236,
        1.6040458679199219,
        1.388980746269226,
        1.098682165145874,
        1.6435149908065796,
        1.386836290359497,
        1.6756470203399658,
        1.4009125232696533,
        1.7343710660934448,
        1.5312020778656006,
        1.7671929597854614,
        1.3132742643356323,
        1.8642038106918335,
        1.4739222526550293,
        1.4251229763031006,
        1.6043777465820312,
        1.2931209802627563,
        1.2793269157409668,
        1.4146325588226318,
        1.1739885807037354,
        1.479957938194275,
        1.3079334497451782,
        1.2303463220596313,
        1.4831857681274414,
        1.4915738105773926,
        1.5536787509918213,
        1.6971625089645386,
        1.3146226406097412,
        1.5923599004745483,
        1.450537085533142,
        1.5536259412765503,
        1.605830430984497,
        1.3582605123519897,
        1.4100341796875,
        1.5835976600646973,
        1.3545407056808472,
        1.459139347076416,
        1.4506027698516846,
        1.487404227256775,
        1.4321792125701904,
        1.2663840055465698,
        1.1625975370407104,
        1.6612658500671387,
        1.3682160377502441,
        1.3113911151885986,
        1.498592495918274,
        1.4928970336914062,
        1.7894080877304077,
        1.2896958589553833,
        1.1821261644363403,
        1.4798082113265991,
        1.4793087244033813,
        1.4579567909240723,
        1.2829853296279907,
        1.6526193618774414,
        1.5581223964691162,
        1.6417808532714844,
        1.4336761236190796,
        1.4037373065948486,
        1.3419705629348755,
        1.6726139783859253,
        1.3294973373413086,
        1.5191848278045654,
        1.574854850769043,
        1.5409432649612427,
        1.24708890914917,
        1.4507664442062378,
        1.5879675149917603,
        1.3470242023468018,
        1.6538112163543701,
        1.3828070163726807,
        1.3027749061584473,
        1.4782518148422241,
        1.3717734813690186,
        1.4056898355484009,
        1.5817545652389526,
        1.466823935508728,
        1.634741187095642,
        1.3932256698608398,
        1.260798454284668,
        1.6233701705932617,
        1.6943546533584595,
        1.5075055360794067,
        1.435044527053833,
        1.2746336460113525,
        1.5137180089950562,
        1.3080366849899292,
        1.5777288675308228,
        1.0974936485290527,
        1.4302133321762085,
        1.8165582418441772,
        1.5579862594604492,
        1.4443355798721313,
        1.5427272319793701,
        1.420424222946167,
        1.5607532262802124,
        1.4077874422073364,
        1.570070743560791,
        1.4339628219604492,
        1.6196789741516113,
        1.4654550552368164,
        1.5771461725234985,
        1.3036279678344727,
        1.3584941625595093,
        1.3525538444519043,
        1.306935429573059,
        1.4454245567321777,
        1.5938266515731812,
        1.3014391660690308,
        1.3622418642044067,
        1.2313463687896729,
        1.2785520553588867,
        1.1729358434677124,
        1.2229812145233154,
        1.7061114311218262,
        1.8398535251617432,
        1.4738162755966187,
        1.359578251838684,
        1.391734004020691,
        1.4280189275741577,
        1.2204935550689697,
        1.512956976890564,
        1.4225397109985352,
        1.4397506713867188,
        1.1572648286819458,
        1.462845802307129,
        1.4812366962432861,
        1.762699842453003,
        1.51100492477417,
        1.495581030845642,
        1.574098825454712,
        1.0338190793991089,
        1.5260096788406372,
        1.2539761066436768,
        1.4476758241653442,
        1.2091490030288696,
        1.4449682235717773,
        1.4986196756362915,
        1.7046339511871338,
        1.6779342889785767,
        1.7320733070373535,
        1.338122844696045,
        1.2876145839691162,
        1.3795162439346313,
        1.7100907564163208,
        1.5091900825500488,
        1.4892590045928955,
        1.3616501092910767,
        1.3550070524215698,
        1.5229488611221313,
        1.7605935335159302,
        1.408130168914795,
        1.4792265892028809,
        1.489844799041748,
        1.4996609687805176,
        1.0951402187347412,
        1.2542762756347656,
        1.2185989618301392,
        1.303657054901123,
        1.6593111753463745,
        1.5198956727981567,
        1.5191128253936768,
        1.5364691019058228,
        1.3844958543777466,
        1.4867889881134033,
        1.580996036529541,
        1.4580539464950562,
        1.2417004108428955,
        1.6720895767211914,
        1.4721368551254272,
        1.505692481994629,
        1.3866139650344849,
        1.663029670715332,
        1.2424241304397583,
        1.3471298217773438,
        2.0576279163360596,
        1.399835467338562,
        1.4574588537216187,
        1.3239452838897705,
        1.7835769653320312,
        1.4777389764785767,
        1.3014459609985352,
        1.4908870458602905,
        1.333408236503601,
        1.7309925556182861,
        1.5320916175842285,
        1.589271903038025,
        0.9458467364311218,
        1.4453774690628052,
        1.504610538482666,
        1.1599030494689941,
        1.423173427581787,
        1.6412588357925415,
        1.3189263343811035,
        1.5425198078155518,
        1.6030806303024292,
        1.357985496520996,
        1.5813342332839966,
        1.4654792547225952,
        1.8641735315322876,
        1.547491192817688,
        1.5095720291137695,
        1.5519405603408813,
        1.5459381341934204,
        1.4487475156784058,
        1.3546645641326904,
        1.6773196458816528,
        1.515143871307373,
        1.3453413248062134,
        1.184565782546997,
        1.310122013092041,
        1.2553753852844238,
        1.4068713188171387,
        1.2428538799285889,
        1.5958229303359985,
        1.2663592100143433,
        1.5093345642089844,
        1.1439250707626343,
        1.2615351676940918,
        1.4762879610061646,
        1.2921632528305054,
        1.3112115859985352,
        1.416806697845459,
        1.2344753742218018,
        1.2976889610290527,
        1.5518914461135864,
        1.5907596349716187,
        1.4683282375335693,
        1.510127305984497,
        1.4227807521820068,
        1.355169415473938,
        1.5695527791976929,
        1.3289507627487183,
        1.316683053970337,
        1.47481369972229,
        1.3289170265197754,
        1.178961157798767,
        1.2579551935195923,
        1.2534300088882446,
        1.2393712997436523,
        1.28926420211792,
        1.2608097791671753,
        1.263694167137146,
        1.47637140750885,
        1.2215778827667236,
        1.4536117315292358,
        1.433340311050415,
        1.457065224647522,
        1.5600497722625732,
        1.0878878831863403,
        1.300999402999878,
        1.5607552528381348,
        1.3388583660125732,
        1.428914189338684,
        1.2251091003417969,
        1.3829673528671265,
        1.5916504859924316,
        1.5775516033172607,
        1.461728572845459,
        1.4840039014816284,
        1.3872543573379517,
        1.3522909879684448,
        1.5209076404571533,
        1.4025481939315796,
        1.467677354812622,
        1.4814982414245605,
        1.3030221462249756,
        1.468284010887146,
        1.2837929725646973,
        1.621634840965271,
        1.5112168788909912,
        1.8697415590286255,
        1.5447579622268677,
        1.5732197761535645,
        1.3278274536132812,
        1.5612324476242065,
        1.4889190196990967,
        1.164625644683838,
        1.4238423109054565,
        1.4273364543914795,
        1.2229951620101929,
        1.308079481124878,
        1.5218043327331543,
        1.3011294603347778,
        1.2708324193954468,
        1.556668996810913,
        1.481350064277649,
        1.2043193578720093,
        1.5514074563980103,
        1.9281549453735352,
        1.424552321434021,
        1.462813377380371,
        1.1056116819381714,
        1.1462271213531494,
        1.2460576295852661,
        1.2687933444976807,
        1.2211813926696777,
        1.2788902521133423,
        1.5151257514953613,
        1.5075355768203735,
        1.3562865257263184,
        1.490622878074646,
        1.2532382011413574,
        1.4536144733428955,
        1.3085174560546875,
        1.4311823844909668,
        1.4202221632003784,
        1.4567679166793823,
        1.4932971000671387,
        1.7184250354766846,
        1.4930310249328613,
        1.1494452953338623,
        1.4120138883590698,
        1.465340256690979,
        1.4280364513397217,
        1.238908052444458,
        1.2424641847610474,
        1.503808617591858,
        1.415102481842041,
        1.0978431701660156,
        1.279249668121338,
        1.4148681163787842,
        1.3869929313659668,
        1.5265103578567505,
        1.5033372640609741,
        1.341618537902832,
        1.216580867767334,
        1.121263027191162,
        1.2916144132614136,
        1.5485213994979858,
        1.4379745721817017,
        1.4593576192855835,
        1.2223927974700928,
        1.4462711811065674,
        1.511256217956543,
        1.5412697792053223,
        1.4090412855148315,
        1.375962495803833,
        1.4154964685440063,
        1.508723497390747,
        1.2720205783843994,
        1.390358567237854,
        1.3594638109207153,
        1.6367971897125244,
        1.4578248262405396,
        1.3374346494674683,
        1.3787652254104614,
        1.2214678525924683,
        1.3078078031539917,
        1.4069372415542603,
        1.3104760646820068,
        1.1172162294387817,
        1.4964087009429932,
        1.3082396984100342,
        1.2458436489105225,
        1.1117748022079468,
        1.1699162721633911,
        1.3409353494644165,
        1.2784630060195923,
        1.6768935918807983,
        1.5391030311584473,
        1.1228225231170654,
        1.245130181312561,
        1.4412407875061035,
        1.1924914121627808,
        1.4291681051254272,
        1.1800739765167236,
        1.149280071258545,
        1.2712019681930542,
        1.3971351385116577,
        1.396207332611084,
        1.5212905406951904,
        1.316918969154358,
        1.3532577753067017,
        1.6023380756378174,
        1.2506515979766846,
        1.4462982416152954,
        1.520681619644165,
        1.4553173780441284,
        1.503293514251709,
        1.2338234186172485,
        1.371550440788269,
        1.4399077892303467,
        1.3406944274902344,
        1.3179866075515747,
        1.4169857501983643,
        1.2011005878448486,
        1.2385437488555908,
        1.5369676351547241,
        1.366544485092163,
        1.2907038927078247,
        1.1493884325027466,
        1.3715901374816895,
        1.4318748712539673,
        1.1792675256729126,
        1.4357924461364746,
        1.4425140619277954,
        1.4476356506347656,
        1.2109284400939941,
        1.3309963941574097,
        1.5679336786270142,
        1.269869327545166,
        1.26881742477417,
        1.4171035289764404,
        1.337632656097412,
        1.3672317266464233,
        1.24531888961792,
        1.3117789030075073,
        1.5080959796905518,
        1.2510769367218018,
        1.2997372150421143,
        1.3190064430236816,
        1.475549340248108,
        1.4397311210632324,
        1.3657968044281006,
        1.5215694904327393,
        1.3966095447540283,
        1.1966012716293335,
        1.5063390731811523,
        1.4307292699813843,
        1.571905493736267,
        1.204482078552246,
        1.5645074844360352,
        1.2772371768951416,
        1.2028740644454956,
        1.1443432569503784,
        1.5707379579544067,
        1.1759146451950073,
        1.4962228536605835,
        1.4600741863250732,
        1.6011852025985718,
        1.263411283493042,
        1.5284607410430908,
        1.3126428127288818,
        1.3775968551635742,
        1.4356797933578491,
        1.3373547792434692,
        1.0699870586395264,
        1.299433946609497,
        1.2012475728988647,
        1.5102713108062744,
        1.5735867023468018,
        1.4468187093734741,
        1.3997490406036377,
        1.3547990322113037,
        1.229174017906189,
        1.2283551692962646,
        1.6283543109893799,
        1.3367809057235718,
        1.2295366525650024,
        1.4045659303665161,
        1.3855379819869995,
        1.1100046634674072,
        1.493353009223938,
        1.6644985675811768,
        1.3264673948287964,
        1.0881956815719604,
        1.3844704627990723,
        1.3383938074111938,
        1.3137733936309814,
        1.3170135021209717,
        1.4774569272994995,
        1.2014145851135254,
        1.605587124824524,
        1.4980173110961914,
        1.7291494607925415,
        1.3035790920257568,
        1.4102261066436768,
        1.3931312561035156,
        1.3862128257751465,
        1.1848714351654053,
        1.4077547788619995,
        1.369521141052246,
        1.3079227209091187,
        1.3873001337051392,
        1.493769884109497,
        1.6898335218429565,
        1.4600950479507446,
        1.3932147026062012,
        1.3870960474014282,
        1.0441251993179321,
        1.3028182983398438,
        1.4723942279815674,
        1.3226439952850342,
        1.3179165124893188,
        1.226609706878662,
        1.2106521129608154,
        1.3380858898162842,
        1.4740370512008667,
        1.2680515050888062,
        1.2983767986297607,
        1.7083929777145386,
        1.4178667068481445,
        1.2240374088287354,
        1.4637714624404907,
        1.4138891696929932,
        1.6999719142913818,
        1.3320995569229126,
        1.392171025276184,
        1.4719021320343018,
        1.3003991842269897,
        1.4858429431915283,
        0.991354763507843,
        1.434023380279541,
        1.5186326503753662,
        1.1652250289916992,
        1.5018718242645264,
        1.5255813598632812,
        1.1053591966629028,
        1.3649863004684448,
        1.311002254486084,
        1.3704171180725098,
        1.6185895204544067,
        1.5193017721176147,
        1.2824654579162598,
        1.472299337387085,
        1.5223965644836426,
        1.3303543329238892,
        1.2562330961227417,
        1.2575095891952515,
        1.3479101657867432,
        1.4759674072265625,
        1.5147082805633545,
        1.5738548040390015,
        1.3289583921432495,
        1.4556080102920532,
        1.5452532768249512,
        1.237056851387024,
        1.3064590692520142,
        1.4195328950881958,
        1.248960018157959,
        1.494126558303833,
        1.2899736166000366,
        1.317308783531189,
        1.2652603387832642,
        1.3418596982955933,
        1.3122448921203613,
        1.4839468002319336,
        1.5614113807678223,
        1.4654546976089478,
        1.543006181716919,
        1.3638033866882324,
        1.3315558433532715,
        1.3768380880355835,
        1.4833331108093262,
        1.404425859451294,
        1.4305871725082397,
        1.2475268840789795,
        1.3657925128936768,
        1.4618107080459595,
        1.2959636449813843,
        1.3046761751174927,
        1.4053820371627808,
        1.2484551668167114,
        1.436578392982483,
        1.3491064310073853,
        1.450502634048462,
        1.5518471002578735,
        1.3202524185180664,
        1.3077212572097778,
        1.2584521770477295,
        1.5684467554092407,
        1.4755010604858398,
        1.242883324623108,
        1.366245985031128,
        1.371309757232666,
        1.5556707382202148,
        1.5957603454589844,
        1.3341180086135864,
        1.1993002891540527,
        1.322640061378479,
        1.1586793661117554,
        1.3820892572402954,
        1.5378929376602173,
        1.8067121505737305,
        1.57720148563385,
        1.0679025650024414,
        1.6351536512374878,
        1.4638268947601318,
        1.2902227640151978,
        1.4034929275512695,
        1.3951867818832397,
        1.2454394102096558,
        1.4749385118484497,
        1.2459720373153687,
        1.2957614660263062,
        1.3914482593536377,
        1.6228936910629272,
        1.2176271677017212,
        1.480021357536316,
        1.1475937366485596,
        1.0726091861724854,
        1.3281474113464355,
        1.1392107009887695,
        1.3813937902450562,
        1.2615278959274292,
        1.4186444282531738,
        1.4001907110214233,
        1.1984997987747192,
        1.2819122076034546,
        1.506483793258667,
        1.3696115016937256,
        1.4500384330749512,
        1.4181203842163086,
        1.5812928676605225,
        1.2694790363311768,
        1.4607675075531006,
        1.4401341676712036,
        1.4049361944198608,
        1.3630764484405518,
        1.3164455890655518,
        1.1678993701934814,
        1.372503399848938,
        1.3069963455200195,
        1.6103054285049438,
        1.220198392868042,
        1.41364324092865,
        1.2496501207351685,
        1.3793432712554932,
        1.344151258468628,
        1.4910489320755005,
        1.3794469833374023,
        1.5145596265792847,
        1.302026391029358,
        1.41843843460083,
        1.3213456869125366,
        1.3073358535766602,
        1.2972784042358398,
        1.3437609672546387,
        1.3452214002609253,
        1.504783272743225,
        1.0934981107711792,
        1.2201006412506104,
        1.5287889242172241,
        1.0543018579483032,
        1.584470510482788,
        1.2479113340377808,
        1.2214833498001099,
        1.4087677001953125,
        1.3827917575836182,
        1.512546420097351,
        1.2830003499984741,
        1.3591541051864624,
        1.2067947387695312,
        1.3704890012741089,
        1.1149852275848389,
        1.616040825843811,
        1.4732333421707153,
        1.3852322101593018,
        1.419571042060852,
        1.5159432888031006,
        0.9926028251647949,
        1.4099689722061157,
        1.1996374130249023,
        1.5022788047790527,
        1.3977328538894653,
        1.1681476831436157,
        1.455285906791687,
        1.5027878284454346,
        1.2801940441131592,
        1.4554808139801025,
        1.356198787689209,
        1.1725038290023804,
        1.247402310371399,
        1.316141963005066,
        1.3404862880706787,
        1.4008477926254272,
        1.5274618864059448,
        1.3391586542129517,
        1.4573866128921509,
        1.2708035707473755,
        1.470649003982544,
        1.2053643465042114,
        1.3773205280303955,
        1.7410995960235596,
        1.5814576148986816,
        1.2223857641220093,
        1.187058925628662,
        1.2430901527404785,
        1.5506043434143066,
        1.3422409296035767,
        1.270080804824829,
        1.4808828830718994,
        1.0400383472442627,
        1.3772234916687012,
        1.5032461881637573,
        1.0471163988113403,
        1.586000680923462,
        1.5712023973464966,
        1.421596646308899,
        1.4378219842910767,
        1.5650832653045654,
        1.403308391571045,
        1.6951849460601807,
        1.447548508644104,
        1.4914159774780273,
        1.3177080154418945,
        1.436454176902771,
        1.2491803169250488,
        1.1812976598739624,
        1.2888187170028687,
        1.4119555950164795,
        1.592931866645813,
        1.2686923742294312,
        1.5486048460006714,
        1.398686170578003,
        1.1273467540740967,
        0.9462091326713562,
        1.2353236675262451,
        1.6186233758926392,
        1.5717027187347412,
        1.3682230710983276,
        1.2149085998535156,
        1.2848526239395142,
        1.377209186553955,
        1.2550965547561646,
        1.554799199104309,
        1.2145253419876099,
        1.5618339776992798,
        1.3397305011749268,
        1.281654953956604,
        1.3898332118988037,
        1.2625786066055298,
        1.1876330375671387,
        1.5352869033813477,
        1.312017560005188,
        1.4922643899917603,
        1.3405239582061768,
        1.5374411344528198,
        1.2426211833953857,
        1.5051437616348267,
        1.1032207012176514,
        1.156342625617981,
        1.1622189283370972,
        1.1903600692749023,
        1.2986297607421875,
        1.5568122863769531,
        1.4613338708877563,
        1.41890549659729,
        1.4690468311309814,
        1.2057667970657349,
        1.400070309638977,
        1.3064100742340088,
        1.5765637159347534,
        1.2436962127685547,
        1.4116822481155396,
        1.0596067905426025,
        1.288258671760559,
        1.0422606468200684,
        1.2779077291488647,
        1.3801029920578003,
        1.2570840120315552,
        1.2912555932998657,
        1.3667728900909424,
        1.427811861038208,
        1.2468925714492798,
        1.3701661825180054,
        1.2793025970458984,
        1.1790704727172852,
        1.4204306602478027,
        1.492071270942688,
        1.4601327180862427,
        1.2810733318328857,
        1.1973298788070679,
        1.4008886814117432,
        1.1892000436782837,
        1.2764984369277954,
        1.4096604585647583,
        1.3293969631195068,
        1.3726047277450562,
        1.2552189826965332,
        1.179409384727478,
        1.4987787008285522,
        1.3471977710723877,
        1.3090213537216187,
        1.3517869710922241,
        1.4502633810043335,
        1.4885172843933105,
        1.1731606721878052,
        1.583163857460022,
        1.331520676612854,
        1.3279110193252563,
        1.3841601610183716,
        1.702643632888794,
        1.2095211744308472,
        1.3616389036178589,
        1.4320586919784546,
        1.6829622983932495,
        1.2513470649719238,
        1.092517375946045,
        1.0093950033187866,
        1.4678229093551636,
        1.3996309041976929,
        1.5663644075393677,
        1.3299864530563354,
        1.1460586786270142,
        1.0598361492156982,
        1.545627474784851,
        1.1904253959655762,
        1.3802313804626465,
        1.5575488805770874,
        1.3417950868606567,
        1.2655127048492432,
        1.5021246671676636,
        1.4173898696899414,
        1.1639348268508911,
        1.292533278465271,
        1.3276692628860474,
        1.270413875579834,
        1.1148808002471924,
        1.4783190488815308,
        1.1653625965118408,
        1.3048336505889893,
        1.2494128942489624,
        1.4833563566207886,
        1.4821337461471558,
        1.4053493738174438,
        1.2909948825836182,
        1.3179844617843628,
        1.3136858940124512,
        1.3736014366149902,
        1.584503173828125,
        1.4127840995788574,
        1.3829944133758545,
        1.0407090187072754,
        1.2620071172714233,
        1.0700355768203735,
        1.176133632659912,
        1.530716896057129,
        1.2807302474975586,
        1.2918893098831177,
        1.3867638111114502,
        1.2373335361480713,
        1.4608906507492065,
        1.4615100622177124,
        1.4713685512542725,
        1.300093412399292,
        1.3412339687347412,
        0.9585545063018799,
        1.3302125930786133,
        1.242596983909607,
        1.3159277439117432,
        1.5735387802124023,
        1.2060273885726929,
        1.2091660499572754,
        1.133793830871582,
        1.4643752574920654,
        1.6932107210159302,
        1.0400041341781616,
        1.485266923904419,
        1.2239415645599365,
        1.3462305068969727,
        1.3230520486831665,
        1.318040132522583,
        1.3929564952850342,
        1.2728315591812134,
        1.7661648988723755,
        1.1827112436294556,
        1.3272771835327148,
        1.4264724254608154,
        1.4592605829238892,
        1.517208218574524,
        1.3961024284362793,
        1.352739691734314,
        1.3424410820007324,
        0.9484530687332153,
        1.4737628698349,
        1.1313552856445312,
        1.5499932765960693,
        1.2690750360488892,
        1.396161675453186,
        1.2738659381866455,
        1.3586113452911377,
        1.1715519428253174,
        1.3624505996704102,
        1.2315963506698608,
        1.3560479879379272,
        1.3802504539489746,
        1.2734652757644653,
        1.5480334758758545,
        1.3014618158340454,
        1.2390925884246826,
        1.2206318378448486,
        1.1272391080856323,
        1.3494398593902588,
        1.250144362449646,
        1.1458920240402222,
        1.5967234373092651,
        1.4589842557907104,
        1.3596111536026,
        1.2519538402557373,
        1.3175387382507324,
        1.4447219371795654,
        1.2133888006210327,
        1.352976679801941,
        1.4550814628601074,
        1.340680718421936,
        1.4429538249969482,
        1.245926022529602,
        1.2470794916152954,
        1.1574771404266357,
        1.3856338262557983,
        1.2046340703964233,
        1.291896939277649,
        1.2269765138626099,
        1.7219735383987427,
        1.304754376411438,
        1.2867341041564941,
        1.2724531888961792,
        1.5886040925979614,
        1.3292651176452637,
        1.4377490282058716,
        1.334667682647705,
        1.3268319368362427,
        1.3469741344451904,
        1.2237082719802856,
        1.347009539604187,
        1.0957667827606201,
        1.2949029207229614,
        1.3236314058303833,
        1.278124213218689,
        1.2490774393081665,
        1.3429784774780273,
        1.2033967971801758,
        1.6642570495605469,
        1.4147017002105713,
        1.2250558137893677,
        1.4321224689483643,
        1.2143597602844238,
        1.2025642395019531,
        1.3612033128738403,
        1.378717303276062,
        1.3672147989273071,
        1.3045347929000854,
        1.2236459255218506,
        1.4392160177230835,
        1.3531887531280518,
        1.3965507745742798,
        1.2908636331558228,
        1.5857367515563965,
        1.3624533414840698,
        1.1721986532211304,
        1.3145511150360107,
        1.602250099182129,
        1.3726463317871094,
        1.1645419597625732,
        1.4831677675247192,
        1.5150305032730103,
        1.668853759765625,
        1.20137619972229,
        1.424315333366394,
        1.118485450744629,
        1.4417098760604858,
        1.4304200410842896,
        0.9973698258399963,
        1.4271774291992188,
        1.1966183185577393,
        1.4756735563278198,
        1.1360076665878296,
        1.237255573272705,
        1.6694868803024292,
        1.398579716682434,
        1.2848364114761353,
        1.5177602767944336,
        1.1314873695373535,
        1.4364407062530518,
        1.3584189414978027,
        1.357851505279541,
        1.3880119323730469,
        1.5020020008087158,
        1.2398823499679565,
        1.1825636625289917,
        0.8891746997833252,
        1.1218457221984863,
        1.2417521476745605,
        1.4917547702789307,
        1.3766461610794067,
        1.2968579530715942,
        1.1434504985809326,
        1.195735216140747,
        1.2502027750015259,
        1.3847975730895996,
        1.2869391441345215,
        1.2890477180480957,
        1.5371588468551636,
        1.2768408060073853,
        1.0980900526046753,
        1.4042866230010986,
        1.3347777128219604,
        1.6546905040740967,
        1.3102144002914429,
        1.2842795848846436,
        1.6470531225204468,
        1.3098351955413818,
        1.402741551399231
    ],
    "generative_model": "{\"class_name\": \"Sequential\", \"config\": {\"name\": \"sequential_1\", \"layers\": [{\"class_name\": \"InputLayer\", \"config\": {\"batch_input_shape\": [1, null], \"dtype\": \"float32\", \"sparse\": false, \"ragged\": false, \"name\": \"embedding_1_input\"}}, {\"class_name\": \"Embedding\", \"config\": {\"name\": \"embedding_1\", \"trainable\": true, \"batch_input_shape\": [1, null], \"dtype\": \"float32\", \"input_dim\": 64, \"output_dim\": 256, \"embeddings_initializer\": {\"class_name\": \"RandomUniform\", \"config\": {\"minval\": -0.05, \"maxval\": 0.05, \"seed\": null}}, \"embeddings_regularizer\": null, \"activity_regularizer\": null, \"embeddings_constraint\": null, \"mask_zero\": false, \"input_length\": null}}, {\"class_name\": \"LSTM\", \"config\": {\"name\": \"lstm_1\", \"trainable\": true, \"dtype\": \"float32\", \"return_sequences\": true, \"return_state\": false, \"go_backwards\": false, \"stateful\": true, \"unroll\": false, \"time_major\": false, \"units\": 256, \"activation\": \"tanh\", \"recurrent_activation\": \"sigmoid\", \"use_bias\": true, \"kernel_initializer\": {\"class_name\": \"GlorotUniform\", \"config\": {\"seed\": null}}, \"recurrent_initializer\": {\"class_name\": \"GlorotUniform\", \"config\": {\"seed\": null}}, \"bias_initializer\": {\"class_name\": \"Zeros\", \"config\": {}}, \"unit_forget_bias\": true, \"kernel_regularizer\": null, \"recurrent_regularizer\": null, \"bias_regularizer\": null, \"activity_regularizer\": null, \"kernel_constraint\": null, \"recurrent_constraint\": null, \"bias_constraint\": null, \"dropout\": 0.0, \"recurrent_dropout\": 0.0, \"implementation\": 2}}, {\"class_name\": \"Dense\", \"config\": {\"name\": \"dense_1\", \"trainable\": true, \"dtype\": \"float32\", \"units\": 64, \"activation\": \"linear\", \"use_bias\": true, \"kernel_initializer\": {\"class_name\": \"GlorotUniform\", \"config\": {\"seed\": null}}, \"bias_initializer\": {\"class_name\": \"Zeros\", \"config\": {}}, \"kernel_regularizer\": null, \"bias_regularizer\": null, \"activity_regularizer\": null, \"kernel_constraint\": null, \"bias_constraint\": null}}]}, \"keras_version\": \"2.9.0\", \"backend\": \"tensorflow\"}"
}